[
    {
        "id": 1033942837,
        "game": "ксго"
    },
    {
        "id": 1033942837,
        "game": "Stray"
    },
    {
        "id": 1127824573,
        "game": "For The King"
    },
    {
        "id": 1127824573,
        "game": "Human: Fall Flat"
    },
    {
        "id": 5014629022,
        "game": "For The King"
    },
    {
        "id": 865715505,
        "game": "Crysis 3 Remastered"
    },
    {
        "id": 1127824573,
        "game": "For The King"
    },
    {
        "id": 5916961672,
        "game": "For The King"
    },
    {
        "id": 1033942837,
        "game": "Human: Fall Flat"
    },
    {
        "id": 1127824573,
        "game": "Demonologist"
    },
    {
        "id": 1127824573,
        "game": "Demonologist"
    },
    {
        "id": 1127824573,
        "game": "X4: Foundations"
    },
    {
        "id": 1127824573,
        "game": "No Man's Sky"
    },
    {
        "id": 1033942837,
        "game": "Human: Fall Flat"
    },
    {
        "id": 1033942837,
        "game": "X4: Foundations"
    },
    {
        "id": 1127824573,
        "game": "Bloons TD 6"
    },
    {
        "id": 1127824573,
        "game": ";ikw4g"
    },
    {
        "id": 1127824573,
        "game": "Bloons TD 6"
    },
    {
        "id": 5014629022,
        "game": "No Man's Sky"
    },
    {
        "id": 5916961672,
        "game": "hades"
    },
    {
        "id": 5916961672,
        "game": "Hades"
    }
]